{
  "id": "Alife.Function.Speech.CosyVoice2",
  "name": "CosyVoice2语音合成",
  "author": "doro",
  "description": "基于CosyVoice2 API的语音合成插件",

  "tags": [
    "语音模型"
  ],

  "dependencies": {
    "Alife.Function.Speech": ""
  },

  "environments": {
    "nuget": {},
    "pip": {}
  },

  "releases": {
    "1.0.1": {
      "date": "2026-06-19",
      "note": "新增UI配置面板、自定义服务路径、自动启动守护、健康检查与重启、请求重试与缓存",
      "file": "https://github.com/L134283/Alife-CosyVoice2/releases/download/1.0.1/Alife.Function.Speech.CosyVoiceTTS.zip"
    },
    "1.0.0": {
      "date": "2026-06-16",
      "note": "初始版本",
      "file": "https://github.com/L134283/Alife-CosyVoice2/releases/download/1.0.0/CosyVoice2.zip"
    }
  }
}
